{
    "mcpServers": {
        "weather": {
            "command": "java",
            "args": [
                "-Dspring.ai.mcp.server.stdio=true",
                "-Dspring.main.web-application-type=none",
                "-Dlogging.pattern.console=",
                "-jar",
                "D:\\open_sources\\spring-ai-alibaba-examples\\spring-ai-alibaba-mcp-example\\spring-ai-alibaba-mcp-build-example\\mcp-stdio-server-example\\target\\mcp-stdio-server-example-1.0.0.jar"
            ],
            "env": {}
        }
    }
}
